 outer:
 for (int i = 2; i < 1000; i++) {
  for (int j = 2; j < i; j++) {
    if (i % j == 0)
      continue outer;
  }
  System.out.println (i);
 }
 Code:
  0:   iconst_2
  1:   istore_1
  2:   iload_1
  3:   sipush  1000
  6:   if_icmpge       44
  9:   iconst_2
  10:  istore_2
  11:  iload_2
  12:  iload_1
  13:  if_icmpge       31
  16:  iload_1
  17:  iload_2
  18:  irem             # remainder
  19:  ifne    25
  22:  goto    38
  25:  iinc    2, 1
  28:  goto    11
  31:  getstatic       #84; //Field java/lang/System.out:Ljava/io/PrintStream;
  34:  iload_1
  35:  invokevirtual   #85; //Method java/io/PrintStream.println:(I)V
  38:  iinc    1, 1
  41:  goto    2
  44:  return
public class Foo {
  public static void main(final String[] args) {
    System.out.println("This is a simple example of decompilation using javap");
    a();
    b();
  }
	
  public static void a() {
    System.out.println("Now we are calling a function...");
  }

  public static void b() {
    System.out.println("...and now we are calling b");
  }
}
$javap Foo
Compiled from "Foo.java"
public class Foo extends java.lang.Object {
    public Foo();
    public static void main(java.lang.String[]);
    public static void a();
    public static void b();
}
$javap -c Foo
Compiled from "Foo.java"
public class Foo extends java.lang.Object{
public Foo();
  Code:
   0:   aload_0
   1:   invokespecial   #1; //Method java/lang/Object."<init>":()V
   4:   return

public static void main(java.lang.String[]);
  Code:
   0:   getstatic       #2; //Field java/lang/System.out:Ljava/io/PrintStream;
   3:   ldc             #3; //String This is a simple example of decompilation using javap
   5:   invokevirtual   #4; //Method java/io/PrintStream.println:(Ljava/lang/String;)V
   8:   invokestatic    #5; //Method a:()V
   11:  invokestatic    #6; //Method b:()V
   14:  return

public static void a();
  Code:
   0:   getstatic       #2; //Field java/lang/System.out:Ljava/io/PrintStream;
   3:   ldc             #7; //String Now we are calling a function...
   5:   invokevirtual   #4; //Method java/io/PrintStream.println:(Ljava/lang/String;)V
   8:   return

public static void b();
  Code:
   0:   getstatic       #2; //Field java/lang/System.out:Ljava/io/PrintStream;
   3:   ldc             #8; //String ...and now we are calling b
   5:   invokevirtual   #4; //Method java/io/PrintStream.println:(Ljava/lang/String;)V
   8:   return

}
